evtpooling/__init__.py
evtpooling/utils.py
evtpooling/alpha/__init__.py
evtpooling/alpha/iid.py
evtpooling/alpha/plots.py
evtpooling/alpha/testing.py
evtpooling/constants/__init__.py
evtpooling/constants/constants.py
evtpooling/constants/etl_defaults.py
evtpooling/etl/__init__.py
evtpooling/etl/etl.py
evtpooling/etl/extract.py
evtpooling/etl/load.py
evtpooling/etl/transform.py
evtpooling/evaluation/__init__.py
evtpooling/evaluation/backtesting.py
evtpooling/pooling/__init__.py
evtpooling/pooling/hmix.py
evtpooling/pooling/kmeans.py
evtpooling/pooling/rmtc.py
evtpooling-0.3.2.dist-info/licenses/LICENSE
evtpooling-0.3.2.dist-info/METADATA
evtpooling-0.3.2.dist-info/WHEEL
evtpooling-0.3.2.dist-info/top_level.txt
evtpooling-0.3.2.dist-info/RECORD
