Metadata-Version: 2.4
Name: evtpooling
Version: 0.3.2
Summary: evtpooling contains the framework needed to improve tail risk forecasts
Author: J.T. Kim
Author-email: "J.T. Kim" <567233jk@eur.nl>
Maintainer-email: "J.T. Kim" <567233jk@eur.nl>
License-Expression: MIT
Project-URL: bugs, https://github.com/JTKimQF/evtpooling/issues
Project-URL: changelog, https://github.com/JTKimQF/evtpooling/blob/master/changelog.md
Project-URL: homepage, https://github.com/JTKimQF/evtpooling
Requires-Python: >=3.9
License-File: LICENSE
Requires-Dist: pandas
Requires-Dist: chardet
Requires-Dist: openpyxl
Requires-Dist: pyarrow
Requires-Dist: rapidfuzz
Provides-Extra: dev
Requires-Dist: coverage; extra == "dev"
Requires-Dist: mypy; extra == "dev"
Requires-Dist: pytest; extra == "dev"
Requires-Dist: ruff; extra == "dev"
Dynamic: author
Dynamic: license-file
